hpcs-0.7.0.dist-info/WHEEL
hpcs-0.7.0.dist-info/entry_points.txt
hpcs-0.7.0.dist-info/top_level.txt
hpcs-0.7.0.dist-info/METADATA
hpcs-0.7.0.dist-info/RECORD
hpcs-0.7.0.dist-info/licenses/LICENSE
hpcs/_simd.c
hpcs/_core.c
hpcs/cli.py
hpcs/_simd.pyx
hpcs/_simd.cpython-311-x86_64-linux-gnu.so
hpcs/__init__.py
hpcs/_core.pyx
hpcs/_core.cpython-311-x86_64-linux-gnu.so
hpcs.libs/libquadmath-96973f99.so.0.0.0
hpcs.libs/libgomp-a34b3233.so.1.0.0
hpcs.libs/libgfortran-040039e1.so.5.0.0
