Metadata-Version: 2.4
Name: hpcs
Version: 0.7.0
Summary: CPU-optimized statistical computing library with SIMD vectorization and OpenMP parallelization for massive datasets (10M+ records)
Author: HPCSeries Core Contributors
License: MIT
Project-URL: Homepage, https://github.com/hpcseries/HPCSeriesCore
Project-URL: Repository, https://github.com/hpcseries/HPCSeriesCore
Project-URL: Documentation, https://github.com/hpcseries/HPCSeriesCore#documentation
Project-URL: Changelog, https://github.com/hpcseries/HPCSeriesCore/blob/main/CHANGELOG.md
Project-URL: Issues, https://github.com/hpcseries/HPCSeriesCore/issues
Project-URL: Source Code, https://github.com/hpcseries/HPCSeriesCore
Project-URL: Performance Docs, https://github.com/hpcseries/HPCSeriesCore/blob/main/docs/PERFORMANCE.md
Project-URL: AWS Deployment, https://github.com/hpcseries/HPCSeriesCore/blob/main/docs/AWS_DEPLOYMENT_GUIDE.md
Keywords: hpc,high-performance-computing,statistics,numpy,simd,openmp,vectorization,time-series,rolling-operations,performance
Classifier: Development Status :: 4 - Beta
Classifier: Intended Audience :: Science/Research
Classifier: Intended Audience :: Developers
Classifier: Intended Audience :: Financial and Insurance Industry
Classifier: Operating System :: POSIX :: Linux
Classifier: Operating System :: MacOS
Classifier: Programming Language :: Python :: 3
Classifier: Programming Language :: Python :: 3.8
Classifier: Programming Language :: Python :: 3.9
Classifier: Programming Language :: Python :: 3.10
Classifier: Programming Language :: Python :: 3.11
Classifier: Programming Language :: Python :: 3.12
Classifier: Programming Language :: Python :: Implementation :: CPython
Classifier: Programming Language :: Cython
Classifier: Programming Language :: C
Classifier: Programming Language :: Fortran
Classifier: Topic :: Scientific/Engineering
Classifier: Topic :: Scientific/Engineering :: Mathematics
Classifier: Topic :: Software Development :: Libraries
Classifier: Topic :: Software Development :: Libraries :: Python Modules
Requires-Python: >=3.8
License-File: LICENSE
Requires-Dist: numpy>=1.20
Provides-Extra: dev
Requires-Dist: pytest>=7.0; extra == "dev"
Requires-Dist: pytest-benchmark; extra == "dev"
Requires-Dist: black; extra == "dev"
Requires-Dist: mypy; extra == "dev"
Requires-Dist: ruff; extra == "dev"
Provides-Extra: docs
Requires-Dist: sphinx>=5.0; extra == "docs"
Requires-Dist: sphinx-rtd-theme; extra == "docs"
Requires-Dist: nbsphinx; extra == "docs"
Provides-Extra: examples
Requires-Dist: jupyter; extra == "examples"
Requires-Dist: matplotlib; extra == "examples"
Requires-Dist: pandas; extra == "examples"
Dynamic: license-file
